metasbooks/__init__.py
metasbooks/book.py
metasbooks/metasbooks.py
metasbooks-0.0.5.dist-info/LICENSE
metasbooks-0.0.5.dist-info/METADATA
metasbooks-0.0.5.dist-info/WHEEL
metasbooks-0.0.5.dist-info/top_level.txt
metasbooks-0.0.5.dist-info/RECORD
