Metadata-Version: 2.1
Name: metasbooks
Version: 0.0.5
Summary: Python client for MetasBooks API https://metasbooks.fr
Author-email: Julien Mercier-Rojas <julien@jeckel-lab.fr>
Project-URL: Homepage, https://github.com/jeckel/metasbooks-client
Project-URL: Issues, https://github.com/jeckel/metasbooks-client/issues
Classifier: Programming Language :: Python :: 3
Classifier: License :: OSI Approved :: MIT License
Classifier: Operating System :: OS Independent
Requires-Python: >=3.12
License-File: LICENSE
Requires-Dist: pydantic>=2.8.2
Requires-Dist: requests>=2.32.3
